thag/__init__.py
thag/render.py
thag/runners/__init__.py
thag/runners/browserhttp.py
thag/runners/browserstarlettehttp.py
thag/runners/browserstarlettews.py
thag/runners/guyapp.py
thag/runners/pywebview.py
thag/runners/webhttp.py
thag/tag.py
thag-0.0.5.dist-info/LICENSE
thag-0.0.5.dist-info/WHEEL
thag-0.0.5.dist-info/METADATA
thag-0.0.5.dist-info/RECORD
