Metadata-Version: 2.1
Name: thag
Version: 0.0.5
Summary: GUI toolkit for building GUI toolkits (and create beautiful applications for mobile, web, and desktop from a single python3 codebase)
Home-page: https://github.com/manatlan/thag
License: MIT
Keywords: gui,electron,cef,pywebview,starlette,asyncio,guy,desktop,web,mobile,http,websocket,html
Author: manatlan
Author-email: manatlan@gmail.com
Requires-Python: >=3.7,<4.0
Classifier: License :: OSI Approved :: Apache Software License
Classifier: License :: OSI Approved :: MIT License
Classifier: Operating System :: OS Independent
Classifier: Programming Language :: Python :: 3
Classifier: Programming Language :: Python :: 3.7
Classifier: Programming Language :: Python :: 3.8
Classifier: Topic :: Software Development :: Build Tools
Classifier: Topic :: Software Development :: Libraries :: Python Modules
Project-URL: Documentation, https://github.com/manatlan/thag
Project-URL: Repository, https://github.com/manatlan/thag
